{
  "rule" : "default_component_owner",
  "assignments" : [
    {
      "mergeKey" : "00066c11d6483aa7937f4aceb9f9ab37",
      "cimUsername" : null,
      "ldapServer" : null
    },
    {
      "mergeKey" : "00884ca2a69ee79d3db41f505dc71ce6",
      "cimUsername" : null,
      "ldapServer" : null
    },
    {
      "mergeKey" : "00e3b4bf15902d143a39334b721da919",
      "cimUsername" : null,
      "ldapServer" : null
    },
    {
      "mergeKey" : "0201f1a71bc5e6151d958737e95c0e2e",
      "cimUsername" : null,
      "ldapServer" : null
    },
    {
      "mergeKey" : "04524e0248b24318adf6bc28f88c320e",
      "cimUsername" : null,
      "ldapServer" : null
    },
    {
      "mergeKey" : "04c705792f0a61eb8521bf74f3df0873",
      "cimUsername" : null,
      "ldapServer" : null
    },
    {
      "mergeKey" : "05341e83fc9e018ed61d03fedbed0b58",
      "cimUsername" : null,
      "ldapServer" : null
    },
    {
      "mergeKey" : "0543d4d73b10c20d5706c2da0e82958b",
      "cimUsername" : null,
      "ldapServer" : null
    },
    {
      "mergeKey" : "067d8bf99186548ca096dbbdeb91a517",
      "cimUsername" : null,
      "ldapServer" : null
    },
    {
      "mergeKey" : "08d60e3a3067b6bc1cf9a07ab33a65c2",
      "cimUsername" : null,
      "ldapServer" : null
    },
    {
      "mergeKey" : "0a06869ab0c9f8bd4fcac71c1af12f81",
      "cimUsername" : null,
      "ldapServer" : null
    },
    {
      "mergeKey" : "0a8cab8707a092d2ed77212cd7e3da09",
      "cimUsername" : null,
      "ldapServer" : null
    },
    {
      "mergeKey" : "0aef3a395e5800df67b108e56761ed8c",
      "cimUsername" : null,
      "ldapServer" : null
    },
    {
      "mergeKey" : "0b33a76a17e93e743de7a95e0d0d2ccc",
      "cimUsername" : null,
      "ldapServer" : null
    },
    {
      "mergeKey" : "0cec65909e4c0ba9a188a963260318d3",
      "cimUsername" : null,
      "ldapServer" : null
    },
    {
      "mergeKey" : "0d0b145c02f010ef68a63d2f79629d22",
      "cimUsername" : null,
      "ldapServer" : null
    },
    {
      "mergeKey" : "0d88802555cf441c361cb7ccf40d98a4",
      "cimUsername" : null,
      "ldapServer" : null
    },
    {
      "mergeKey" : "0dd0840f2ea963bb37ffa9e550cc5323",
      "cimUsername" : null,
      "ldapServer" : null
    },
    {
      "mergeKey" : "0f417079820ee26ed3a11667e9406ab9",
      "cimUsername" : null,
      "ldapServer" : null
    },
    {
      "mergeKey" : "10ee27387f4d4fd3a56f8b3562850790",
      "cimUsername" : null,
      "ldapServer" : null
    },
    {
      "mergeKey" : "12c8a651990d0f49664703839ae35435",
      "cimUsername" : null,
      "ldapServer" : null
    },
    {
      "mergeKey" : "1346fa6ca174810536ca65b5a58ccaa0",
      "cimUsername" : null,
      "ldapServer" : null
    },
    {
      "mergeKey" : "1359c03c753ee72438d5c0ee8fc81cf6",
      "cimUsername" : null,
      "ldapServer" : null
    },
    {
      "mergeKey" : "14e2ef739150761ba32901af0e87e733",
      "cimUsername" : null,
      "ldapServer" : null
    },
    {
      "mergeKey" : "1507117cfeb532023a8643a5ee6f36b5",
      "cimUsername" : null,
      "ldapServer" : null
    },
    {
      "mergeKey" : "16b87984d427788a9ed0bd70135d5f5f",
      "cimUsername" : null,
      "ldapServer" : null
    },
    {
      "mergeKey" : "189bce82a31e668f3827b8eb9111e33a",
      "cimUsername" : null,
      "ldapServer" : null
    },
    {
      "mergeKey" : "1cde1c95cec3ee3f401fdf73289c3844",
      "cimUsername" : null,
      "ldapServer" : null
    },
    {
      "mergeKey" : "1d198c39feda08c7b4f4963a6ca5e63d",
      "cimUsername" : null,
      "ldapServer" : null
    },
    {
      "mergeKey" : "1d570b249c8cb5edb9608586ba7cb429",
      "cimUsername" : null,
      "ldapServer" : null
    },
    {
      "mergeKey" : "1e7d4372c59448aec03ba7c734a9da6e",
      "cimUsername" : null,
      "ldapServer" : null
    },
    {
      "mergeKey" : "1eb02f398844a27eabe769568c05927c",
      "cimUsername" : null,
      "ldapServer" : null
    },
    {
      "mergeKey" : "207b42c003d8d3ea6727917b603087a8",
      "cimUsername" : null,
      "ldapServer" : null
    },
    {
      "mergeKey" : "21cb335823817f925affa73ff2f7ea81",
      "cimUsername" : null,
      "ldapServer" : null
    },
    {
      "mergeKey" : "22f4695ad930cfdda8488fed82736a42",
      "cimUsername" : null,
      "ldapServer" : null
    },
    {
      "mergeKey" : "25b55409400d1867f54fdc2d4a7eb2f2",
      "cimUsername" : null,
      "ldapServer" : null
    },
    {
      "mergeKey" : "26237fddfcfe7a70acc598c9b94c6aab",
      "cimUsername" : null,
      "ldapServer" : null
    },
    {
      "mergeKey" : "2631cc39df2cb974645020d7383d895a",
      "cimUsername" : null,
      "ldapServer" : null
    },
    {
      "mergeKey" : "286607c7cab1d7f56699b017310542cc",
      "cimUsername" : null,
      "ldapServer" : null
    },
    {
      "mergeKey" : "29fad93e9a3bf5373eac654626a6ade2",
      "cimUsername" : null,
      "ldapServer" : null
    },
    {
      "mergeKey" : "2d8ba82eb218545a79b85953a8cdd737",
      "cimUsername" : null,
      "ldapServer" : null
    },
    {
      "mergeKey" : "2dc36affa0ebe7ef3a49af38f0b8092d",
      "cimUsername" : null,
      "ldapServer" : null
    },
    {
      "mergeKey" : "2fd59246a3aab46d32550d0dcb60752b",
      "cimUsername" : null,
      "ldapServer" : null
    },
    {
      "mergeKey" : "305459634694b2f50694718480a87aff",
      "cimUsername" : null,
      "ldapServer" : null
    },
    {
      "mergeKey" : "3358e43b85b66cb586f890e4df113ddf",
      "cimUsername" : null,
      "ldapServer" : null
    },
    {
      "mergeKey" : "35579d86054ed8d7a7a070837d9c84a9",
      "cimUsername" : null,
      "ldapServer" : null
    },
    {
      "mergeKey" : "35d507fe6de9e1d6f87b2a0af3136981",
      "cimUsername" : null,
      "ldapServer" : null
    },
    {
      "mergeKey" : "36ddc5bc0a5ef69dedc1e5ff52e9c385",
      "cimUsername" : null,
      "ldapServer" : null
    },
    {
      "mergeKey" : "3705dda5f1ee151cf1c7380301f30247",
      "cimUsername" : null,
      "ldapServer" : null
    },
    {
      "mergeKey" : "392818ca9c11ffbaacf11104f5251bba",
      "cimUsername" : null,
      "ldapServer" : null
    },
    {
      "mergeKey" : "3b35ef96ca45e4b86e14104ceb9a9e4c",
      "cimUsername" : null,
      "ldapServer" : null
    },
    {
      "mergeKey" : "3bb8fb032e048dc33c2f5299025c0103",
      "cimUsername" : null,
      "ldapServer" : null
    },
    {
      "mergeKey" : "3bcb54f6358a792ded05bf84aa8bbf3f",
      "cimUsername" : null,
      "ldapServer" : null
    },
    {
      "mergeKey" : "3f71755f3b2573c7672da2d0a7fa74a3",
      "cimUsername" : null,
      "ldapServer" : null
    },
    {
      "mergeKey" : "40a20e4b3f646ddc5338ea8ad4872ce8",
      "cimUsername" : null,
      "ldapServer" : null
    },
    {
      "mergeKey" : "41d8662b933b0ba72149ccba2c9f8e42",
      "cimUsername" : null,
      "ldapServer" : null
    },
    {
      "mergeKey" : "42c6ab282ce97d8d3780d41366a8a9bb",
      "cimUsername" : null,
      "ldapServer" : null
    },
    {
      "mergeKey" : "44285bf66c252511397d5112efb7ff6e",
      "cimUsername" : null,
      "ldapServer" : null
    },
    {
      "mergeKey" : "4449d70bf43cd29126abe47173b61485",
      "cimUsername" : null,
      "ldapServer" : null
    },
    {
      "mergeKey" : "4523f96b4dcdae2a198ddf9b0c877a2f",
      "cimUsername" : null,
      "ldapServer" : null
    },
    {
      "mergeKey" : "4672e0bb402e4294c6d390208ed665a0",
      "cimUsername" : null,
      "ldapServer" : null
    },
    {
      "mergeKey" : "46abdb5204a7311106cc2babc3faefb2",
      "cimUsername" : null,
      "ldapServer" : null
    },
    {
      "mergeKey" : "4754a8a294cd7652950d391c9ee0a6f2",
      "cimUsername" : null,
      "ldapServer" : null
    },
    {
      "mergeKey" : "48569b3e084de26d6b61e2e336dcf112",
      "cimUsername" : null,
      "ldapServer" : null
    },
    {
      "mergeKey" : "4885c3704bfed15ae038b132041c5db7",
      "cimUsername" : null,
      "ldapServer" : null
    },
    {
      "mergeKey" : "4aad478ab567cd5e63b23f9d594b74e7",
      "cimUsername" : null,
      "ldapServer" : null
    },
    {
      "mergeKey" : "4bd7fe2fcf2b0fce2d47d38264de2197",
      "cimUsername" : null,
      "ldapServer" : null
    },
    {
      "mergeKey" : "4ef4709d05b41e6c8f86fa5e120539dd",
      "cimUsername" : null,
      "ldapServer" : null
    },
    {
      "mergeKey" : "503f3ff0f532c4cac7c665cf205a8cf9",
      "cimUsername" : null,
      "ldapServer" : null
    },
    {
      "mergeKey" : "50761f87d63523a3375ffade95caa04b",
      "cimUsername" : null,
      "ldapServer" : null
    },
    {
      "mergeKey" : "51830e1cb93455592b27c85cc97ea96d",
      "cimUsername" : null,
      "ldapServer" : null
    },
    {
      "mergeKey" : "5216c62b0e3d21c81bc000135175b197",
      "cimUsername" : null,
      "ldapServer" : null
    },
    {
      "mergeKey" : "52b44a62b90672451b9199ea375adf59",
      "cimUsername" : null,
      "ldapServer" : null
    },
    {
      "mergeKey" : "52e7091a7825b6be55701e43c34e416d",
      "cimUsername" : null,
      "ldapServer" : null
    },
    {
      "mergeKey" : "54e51e22fc922aa42c4fc01c84c1690a",
      "cimUsername" : null,
      "ldapServer" : null
    },
    {
      "mergeKey" : "58864afbc3e6beb24cec2055251473b8",
      "cimUsername" : null,
      "ldapServer" : null
    },
    {
      "mergeKey" : "5a370b19fa757c25db23108d2caafd95",
      "cimUsername" : null,
      "ldapServer" : null
    },
    {
      "mergeKey" : "5aa7a94720f5742e8ab80fee37e6fc7e",
      "cimUsername" : null,
      "ldapServer" : null
    },
    {
      "mergeKey" : "5b9ca29f2de90d71ba7baf45d1b27113",
      "cimUsername" : null,
      "ldapServer" : null
    },
    {
      "mergeKey" : "5d7e2db3d9fb0f1a40911886d92951cf",
      "cimUsername" : null,
      "ldapServer" : null
    },
    {
      "mergeKey" : "5f59ff577df68763fdf51df5921b2079",
      "cimUsername" : null,
      "ldapServer" : null
    },
    {
      "mergeKey" : "5f683d164c8dcda026cee57f8e43a82b",
      "cimUsername" : null,
      "ldapServer" : null
    },
    {
      "mergeKey" : "5fb7e7fedeee3c7d2ce9cd00ec81f50e",
      "cimUsername" : null,
      "ldapServer" : null
    },
    {
      "mergeKey" : "5fe2a57d72435b22def4f8d0218946eb",
      "cimUsername" : null,
      "ldapServer" : null
    },
    {
      "mergeKey" : "60a3a909bee9669ad05fe42d7e20fd33",
      "cimUsername" : null,
      "ldapServer" : null
    },
    {
      "mergeKey" : "62698bd91f830799ca52d4ffa7fa2d48",
      "cimUsername" : null,
      "ldapServer" : null
    },
    {
      "mergeKey" : "63056b0f592cbfd3368a1666ab50fa1a",
      "cimUsername" : null,
      "ldapServer" : null
    },
    {
      "mergeKey" : "63b9e7320a79d43b20c06f32eca72002",
      "cimUsername" : null,
      "ldapServer" : null
    },
    {
      "mergeKey" : "644f1e20114422875ed7241a18335b8a",
      "cimUsername" : null,
      "ldapServer" : null
    },
    {
      "mergeKey" : "66134a9b09c6297bb19297f73ccbc792",
      "cimUsername" : null,
      "ldapServer" : null
    },
    {
      "mergeKey" : "666182764e454b3eac8be393d22bd3b3",
      "cimUsername" : null,
      "ldapServer" : null
    },
    {
      "mergeKey" : "67db623554e19499238bae00e235fbc4",
      "cimUsername" : null,
      "ldapServer" : null
    },
    {
      "mergeKey" : "6a8c6e83621d9e787b7895f9eb15ca5b",
      "cimUsername" : null,
      "ldapServer" : null
    },
    {
      "mergeKey" : "6adb9c95c81aeffe0b2fa9ed5ace6dd3",
      "cimUsername" : null,
      "ldapServer" : null
    },
    {
      "mergeKey" : "6b4177def2da0648810b4813f9012477",
      "cimUsername" : null,
      "ldapServer" : null
    },
    {
      "mergeKey" : "6f3a9fdb5371a4b518a234c39cf58213",
      "cimUsername" : null,
      "ldapServer" : null
    },
    {
      "mergeKey" : "7043338f6730dd59a668454f678b2ebf",
      "cimUsername" : null,
      "ldapServer" : null
    },
    {
      "mergeKey" : "70eebc0d147cfaffbd685518a06e932a",
      "cimUsername" : null,
      "ldapServer" : null
    },
    {
      "mergeKey" : "738f4442a1ed7fbfecf0e5a340c27967",
      "cimUsername" : null,
      "ldapServer" : null
    },
    {
      "mergeKey" : "7517de4d2ff590787b93964be76c3ff8",
      "cimUsername" : null,
      "ldapServer" : null
    },
    {
      "mergeKey" : "77281500ae5d3bcaa5a62a3f7781c876",
      "cimUsername" : null,
      "ldapServer" : null
    },
    {
      "mergeKey" : "78416d5a59024793088a08f2edfa3b53",
      "cimUsername" : null,
      "ldapServer" : null
    },
    {
      "mergeKey" : "7863620cfef01fd600f7a63d662963a5",
      "cimUsername" : null,
      "ldapServer" : null
    },
    {
      "mergeKey" : "793b3ddd678b0380b741d6d5ba645398",
      "cimUsername" : null,
      "ldapServer" : null
    },
    {
      "mergeKey" : "79abb719f959363a7600899d38bc577a",
      "cimUsername" : null,
      "ldapServer" : null
    },
    {
      "mergeKey" : "7a7fa4cd667fa6785ab622f5cc7e5b64",
      "cimUsername" : null,
      "ldapServer" : null
    },
    {
      "mergeKey" : "7ac6c3708c059a0ace93799babdf0b61",
      "cimUsername" : null,
      "ldapServer" : null
    },
    {
      "mergeKey" : "7b4d49c8cfa4aec1180b4d50e3a14576",
      "cimUsername" : null,
      "ldapServer" : null
    },
    {
      "mergeKey" : "7e04dc6c095a4b95b1b024b1dfe4bfe4",
      "cimUsername" : null,
      "ldapServer" : null
    },
    {
      "mergeKey" : "7e07354a515098695c0f465ae45e5805",
      "cimUsername" : null,
      "ldapServer" : null
    },
    {
      "mergeKey" : "7f6a8e28255b9d954e33830c1cb90b60",
      "cimUsername" : null,
      "ldapServer" : null
    },
    {
      "mergeKey" : "81b1cbe4ba995a5cc0a85e2f9ad084ac",
      "cimUsername" : null,
      "ldapServer" : null
    },
    {
      "mergeKey" : "81fc8e61e2070985f647214a974eb2f2",
      "cimUsername" : null,
      "ldapServer" : null
    },
    {
      "mergeKey" : "85b292a20b08949dd0fae7f5d44d88dc",
      "cimUsername" : null,
      "ldapServer" : null
    },
    {
      "mergeKey" : "86f402f4ab562d807cda5f2f92b8c538",
      "cimUsername" : null,
      "ldapServer" : null
    },
    {
      "mergeKey" : "877a7b658218fa30a68772a144d9bcfe",
      "cimUsername" : null,
      "ldapServer" : null
    },
    {
      "mergeKey" : "890ea170d64d413de0f3ed770e97cb67",
      "cimUsername" : null,
      "ldapServer" : null
    },
    {
      "mergeKey" : "8bf8cf68f290bdc4cf602efdd1262391",
      "cimUsername" : null,
      "ldapServer" : null
    },
    {
      "mergeKey" : "8d057e53a2433309cbb7e57ebd4da3e7",
      "cimUsername" : null,
      "ldapServer" : null
    },
    {
      "mergeKey" : "8d39d676e47b0ab3a3ba6f4525402604",
      "cimUsername" : null,
      "ldapServer" : null
    },
    {
      "mergeKey" : "8e17b18f6222787fac1a89be80e40415",
      "cimUsername" : null,
      "ldapServer" : null
    },
    {
      "mergeKey" : "8ebb82659ea2a255b8c88af07f49def8",
      "cimUsername" : null,
      "ldapServer" : null
    },
    {
      "mergeKey" : "8ef613966e961db7403aac30f568140e",
      "cimUsername" : null,
      "ldapServer" : null
    },
    {
      "mergeKey" : "920da8e0f49e179a071b433dd0236438",
      "cimUsername" : null,
      "ldapServer" : null
    },
    {
      "mergeKey" : "922e600dd1cb867c18f90179756095b6",
      "cimUsername" : null,
      "ldapServer" : null
    },
    {
      "mergeKey" : "933e4ca482be5607d37f2e368e507ffd",
      "cimUsername" : null,
      "ldapServer" : null
    },
    {
      "mergeKey" : "94371a4ede9a74a963145a0fda7af2d6",
      "cimUsername" : null,
      "ldapServer" : null
    },
    {
      "mergeKey" : "94662a9f92dc50dc36f1007457d6c8b8",
      "cimUsername" : null,
      "ldapServer" : null
    },
    {
      "mergeKey" : "94c0ec1cf7622294193f93c2ea2fcffa",
      "cimUsername" : null,
      "ldapServer" : null
    },
    {
      "mergeKey" : "95281f0c81f83ea24cfe8628512e7eb9",
      "cimUsername" : null,
      "ldapServer" : null
    },
    {
      "mergeKey" : "961604a1efc3655af0756c427b272f2d",
      "cimUsername" : null,
      "ldapServer" : null
    },
    {
      "mergeKey" : "96a07f87615aaf4a85aa31896729ca3a",
      "cimUsername" : null,
      "ldapServer" : null
    },
    {
      "mergeKey" : "97973ba5e52927183efe33c17c00811d",
      "cimUsername" : null,
      "ldapServer" : null
    },
    {
      "mergeKey" : "98d21eea8ef40bbc83456c36300ba0e3",
      "cimUsername" : null,
      "ldapServer" : null
    },
    {
      "mergeKey" : "9ad5b590f58e9c1446e0df1d1641fc5f",
      "cimUsername" : null,
      "ldapServer" : null
    },
    {
      "mergeKey" : "9bf7e36c352ce68999d3b9a605477c19",
      "cimUsername" : null,
      "ldapServer" : null
    },
    {
      "mergeKey" : "9cf2d024db8a7c70f4a06e5b4698be71",
      "cimUsername" : null,
      "ldapServer" : null
    },
    {
      "mergeKey" : "9ee53cd1acdfaa6f9f758295d2e6d910",
      "cimUsername" : null,
      "ldapServer" : null
    },
    {
      "mergeKey" : "9f8545f188fde4d50d3958cc0e6b2738",
      "cimUsername" : null,
      "ldapServer" : null
    },
    {
      "mergeKey" : "a0101ca376c449bdbff6c367ce55c523",
      "cimUsername" : null,
      "ldapServer" : null
    },
    {
      "mergeKey" : "a1e807773408de42b66c80ee00119588",
      "cimUsername" : null,
      "ldapServer" : null
    },
    {
      "mergeKey" : "a245c372a70e99d6191d1a6f26c785e8",
      "cimUsername" : null,
      "ldapServer" : null
    },
    {
      "mergeKey" : "a4a619c08e2f0bfdb0e85ce83cd8a061",
      "cimUsername" : null,
      "ldapServer" : null
    },
    {
      "mergeKey" : "a5335e9385d91a1fefc9310def838060",
      "cimUsername" : null,
      "ldapServer" : null
    },
    {
      "mergeKey" : "a5ae42cc836c6a234faf9e47cbef1bf1",
      "cimUsername" : null,
      "ldapServer" : null
    },
    {
      "mergeKey" : "a883ab11b3b0eec904c2ddbae2047808",
      "cimUsername" : null,
      "ldapServer" : null
    },
    {
      "mergeKey" : "a8be379ef0deaf8318969c51bd424de2",
      "cimUsername" : null,
      "ldapServer" : null
    },
    {
      "mergeKey" : "a90be04ee4bf6c9a753d861e11dca30d",
      "cimUsername" : null,
      "ldapServer" : null
    },
    {
      "mergeKey" : "aa3c60d749db061c40d8ca4457477204",
      "cimUsername" : null,
      "ldapServer" : null
    },
    {
      "mergeKey" : "aa488d1798babbdf67a73408188d33d7",
      "cimUsername" : null,
      "ldapServer" : null
    },
    {
      "mergeKey" : "aafc459971b08271d304dc6ae778c6b9",
      "cimUsername" : null,
      "ldapServer" : null
    },
    {
      "mergeKey" : "ac223a56577427176e9918582d08c9c4",
      "cimUsername" : null,
      "ldapServer" : null
    },
    {
      "mergeKey" : "ac69549becbf8f5653f37d76eae13af6",
      "cimUsername" : null,
      "ldapServer" : null
    },
    {
      "mergeKey" : "acdefb0f6762211690447e90ab806649",
      "cimUsername" : null,
      "ldapServer" : null
    },
    {
      "mergeKey" : "ad5708d0f39641b43ef86476fe35e19b",
      "cimUsername" : null,
      "ldapServer" : null
    },
    {
      "mergeKey" : "add366388df6b03c74795e5312f34384",
      "cimUsername" : null,
      "ldapServer" : null
    },
    {
      "mergeKey" : "aed7a253e92a168a0900faa02861537a",
      "cimUsername" : null,
      "ldapServer" : null
    },
    {
      "mergeKey" : "b003d26729b58a3073a080e87551bebc",
      "cimUsername" : null,
      "ldapServer" : null
    },
    {
      "mergeKey" : "b0885c0e3c29ac634529aa6372ed180e",
      "cimUsername" : null,
      "ldapServer" : null
    },
    {
      "mergeKey" : "b0bc714bc7994b0e981a61b278de4493",
      "cimUsername" : null,
      "ldapServer" : null
    },
    {
      "mergeKey" : "b14112a4ff6ffbad8bbb654c0970e08e",
      "cimUsername" : null,
      "ldapServer" : null
    },
    {
      "mergeKey" : "b4d4d7f88ee08f2b13d79d2d34bf42b0",
      "cimUsername" : null,
      "ldapServer" : null
    },
    {
      "mergeKey" : "b557adb654b4adf42e2d379df2d1e1eb",
      "cimUsername" : null,
      "ldapServer" : null
    },
    {
      "mergeKey" : "b55edd0dae409f6a5212b9f13b1a54ed",
      "cimUsername" : null,
      "ldapServer" : null
    },
    {
      "mergeKey" : "b67fbeb6c87ce84b7c856157a97ab3fb",
      "cimUsername" : null,
      "ldapServer" : null
    },
    {
      "mergeKey" : "b88fade4e8411c06c673e28eb917516b",
      "cimUsername" : null,
      "ldapServer" : null
    },
    {
      "mergeKey" : "b8e37eb689c7c86a2d3d0ff49fb9c07d",
      "cimUsername" : null,
      "ldapServer" : null
    },
    {
      "mergeKey" : "bb07c70cb16f5cd9a51b2119548cb85e",
      "cimUsername" : null,
      "ldapServer" : null
    },
    {
      "mergeKey" : "bbd9816c982ee4bed851ab5eb08c1959",
      "cimUsername" : null,
      "ldapServer" : null
    },
    {
      "mergeKey" : "bc7843642d2363c0d05f714749315d1e",
      "cimUsername" : null,
      "ldapServer" : null
    },
    {
      "mergeKey" : "be32b58abc054fa84d9d3066173be21c",
      "cimUsername" : null,
      "ldapServer" : null
    },
    {
      "mergeKey" : "c042505f3337e79b3268b71cb8a98000",
      "cimUsername" : null,
      "ldapServer" : null
    },
    {
      "mergeKey" : "c122ac0af3cfd6a2eac525737737a1c6",
      "cimUsername" : null,
      "ldapServer" : null
    },
    {
      "mergeKey" : "c3c2539bbdbaf9e5f43e68ae4da73a33",
      "cimUsername" : null,
      "ldapServer" : null
    },
    {
      "mergeKey" : "c5ea10fca40564203b6e8a81edc04612",
      "cimUsername" : null,
      "ldapServer" : null
    },
    {
      "mergeKey" : "c6a381cdf6205b650ea0b62c0ec115ae",
      "cimUsername" : null,
      "ldapServer" : null
    },
    {
      "mergeKey" : "c838d97d2c688fb7f90c31b1b4135b32",
      "cimUsername" : null,
      "ldapServer" : null
    },
    {
      "mergeKey" : "c8395b275178bf4111636af577938489",
      "cimUsername" : null,
      "ldapServer" : null
    },
    {
      "mergeKey" : "c94d78becd35fa6fafb0b1d87a711005",
      "cimUsername" : null,
      "ldapServer" : null
    },
    {
      "mergeKey" : "c94e061321f38464d8a441011b7c4fb0",
      "cimUsername" : null,
      "ldapServer" : null
    },
    {
      "mergeKey" : "cc5993f5e607d5e850ca159227abf627",
      "cimUsername" : null,
      "ldapServer" : null
    },
    {
      "mergeKey" : "ced2e7c60314d6e7e28f12bfa183542f",
      "cimUsername" : null,
      "ldapServer" : null
    },
    {
      "mergeKey" : "d0dd6aca803f2fd10a6e02e8d1d28099",
      "cimUsername" : null,
      "ldapServer" : null
    },
    {
      "mergeKey" : "d12feac71e55de6ae404f920cc227918",
      "cimUsername" : null,
      "ldapServer" : null
    },
    {
      "mergeKey" : "d1383ead147860f0673a2b86d3103f00",
      "cimUsername" : null,
      "ldapServer" : null
    },
    {
      "mergeKey" : "d1e5afdfadcd61bc3c8c161e1fbc9b6e",
      "cimUsername" : null,
      "ldapServer" : null
    },
    {
      "mergeKey" : "d3a736aac10556c8628ea3d7f45fd2b3",
      "cimUsername" : null,
      "ldapServer" : null
    },
    {
      "mergeKey" : "d3b8335a27dc34a39dcbc23eeb37f34d",
      "cimUsername" : null,
      "ldapServer" : null
    },
    {
      "mergeKey" : "d456f01d4d73e6decb7635bb59cb8d3d",
      "cimUsername" : null,
      "ldapServer" : null
    },
    {
      "mergeKey" : "d474827410f652087cc0db2de6960f99",
      "cimUsername" : null,
      "ldapServer" : null
    },
    {
      "mergeKey" : "d533066e04723a18a69749625eba0657",
      "cimUsername" : null,
      "ldapServer" : null
    },
    {
      "mergeKey" : "d588f4db873ff955aabaa7dcafc72a86",
      "cimUsername" : null,
      "ldapServer" : null
    },
    {
      "mergeKey" : "d64efdb4598087cb4e3dc90092c710dd",
      "cimUsername" : null,
      "ldapServer" : null
    },
    {
      "mergeKey" : "da4665966b7e8b9d02c113db0f71867b",
      "cimUsername" : null,
      "ldapServer" : null
    },
    {
      "mergeKey" : "dbc3474b0bc253a21604f5941edb1364",
      "cimUsername" : null,
      "ldapServer" : null
    },
    {
      "mergeKey" : "dd15080dad2efb4051241fb69522cb86",
      "cimUsername" : null,
      "ldapServer" : null
    },
    {
      "mergeKey" : "dd898e9a0dee9fc3cc180fb3e2e5094c",
      "cimUsername" : null,
      "ldapServer" : null
    },
    {
      "mergeKey" : "dddef4b3ed0479c7621f1fb9b582b06f",
      "cimUsername" : null,
      "ldapServer" : null
    },
    {
      "mergeKey" : "de63de4b396176f4050529793c4ad84a",
      "cimUsername" : null,
      "ldapServer" : null
    },
    {
      "mergeKey" : "e0fe615c62c0d41ee5436e5cbf3b680f",
      "cimUsername" : null,
      "ldapServer" : null
    },
    {
      "mergeKey" : "e1c63021c1329c894e792e66269a4caa",
      "cimUsername" : null,
      "ldapServer" : null
    },
    {
      "mergeKey" : "e285b03eaf9ef0e9b2be742a8f2369e7",
      "cimUsername" : null,
      "ldapServer" : null
    },
    {
      "mergeKey" : "e28ccad9122e73ba5cc126080f5a790a",
      "cimUsername" : null,
      "ldapServer" : null
    },
    {
      "mergeKey" : "e2a6441aa039b64798ce9da8349ce569",
      "cimUsername" : null,
      "ldapServer" : null
    },
    {
      "mergeKey" : "e958a570523fe837ae847446bf93cfed",
      "cimUsername" : null,
      "ldapServer" : null
    },
    {
      "mergeKey" : "edf91d6f24a20431f27175a7aa182fa4",
      "cimUsername" : null,
      "ldapServer" : null
    },
    {
      "mergeKey" : "eeec44880a91aaeaa9a26e2bc4af8e72",
      "cimUsername" : null,
      "ldapServer" : null
    },
    {
      "mergeKey" : "ef9d7a11bdddaf809f057f2617b3a046",
      "cimUsername" : null,
      "ldapServer" : null
    },
    {
      "mergeKey" : "f163985379a83d4302cdd150a793b7ce",
      "cimUsername" : null,
      "ldapServer" : null
    },
    {
      "mergeKey" : "f1bc7f33a9bce0d1341c2971b9725a91",
      "cimUsername" : null,
      "ldapServer" : null
    },
    {
      "mergeKey" : "f2b47cd39a178dfca9bee5fc8660a8e2",
      "cimUsername" : null,
      "ldapServer" : null
    },
    {
      "mergeKey" : "f2f7b9bab36af815d9512e0d827ed19e",
      "cimUsername" : null,
      "ldapServer" : null
    },
    {
      "mergeKey" : "f2fe79475f92bec2d88710aae9793c2b",
      "cimUsername" : null,
      "ldapServer" : null
    },
    {
      "mergeKey" : "f42dd71f71b85ba8593b08a1720ab908",
      "cimUsername" : null,
      "ldapServer" : null
    },
    {
      "mergeKey" : "f435cdd328b6c5ff034dc649f794d380",
      "cimUsername" : null,
      "ldapServer" : null
    },
    {
      "mergeKey" : "f51509334428b43a2c6ad9e4c74a13e1",
      "cimUsername" : null,
      "ldapServer" : null
    },
    {
      "mergeKey" : "f5d249ff072b1f146fd94d7df992e556",
      "cimUsername" : null,
      "ldapServer" : null
    },
    {
      "mergeKey" : "f7495c22be388a9509863957a49edfc3",
      "cimUsername" : null,
      "ldapServer" : null
    },
    {
      "mergeKey" : "fa52d80a69001b317b91b1d5c6d6ed86",
      "cimUsername" : null,
      "ldapServer" : null
    },
    {
      "mergeKey" : "fbf334f60734baf522ffb377280737fb",
      "cimUsername" : null,
      "ldapServer" : null
    },
    {
      "mergeKey" : "feda0ec7a92a000f888c9c605d7d8f05",
      "cimUsername" : null,
      "ldapServer" : null
    }
  ]
}
